LICENSE
MANIFEST.in
README.rst
setup.cfg
setup.py
django_newswall.egg-info/PKG-INFO
django_newswall.egg-info/SOURCES.txt
django_newswall.egg-info/dependency_links.txt
django_newswall.egg-info/not-zip-safe
django_newswall.egg-info/requires.txt
django_newswall.egg-info/top_level.txt
newswall/__init__.py
newswall/admin.py
newswall/feeds.py
newswall/models.py
newswall/urls.py
newswall/views.py
newswall/locale/de/LC_MESSAGES/django.mo
newswall/locale/de/LC_MESSAGES/django.po
newswall/management/__init__.py
newswall/management/commands/__init__.py
newswall/management/commands/update_newswall.py
newswall/migrations/0001_initial.py
newswall/migrations/0002_auto__chg_field_story_title.py
newswall/migrations/0003_auto__chg_field_story_title__chg_field_story_image_url.py
newswall/migrations/__init__.py
newswall/providers/__init__.py
newswall/providers/base.py
newswall/providers/elephantblog.py
newswall/providers/fb_graph_feed.py
newswall/providers/feed.py
newswall/providers/twitter.py
newswall/templates/newswall/story_archive.html
newswall/templates/newswall/story_detail.html
newswall/templatetags/__init__.py
newswall/templatetags/newswall_tags.py